<?xml version="1.0" encoding="UTF-8"?>
<!DOCTYPE mapper PUBLIC "-//mybatis.org//DTD Mapper 3.0//EN" "http://mybatis.org/dtd/mybatis-3-mapper.dtd">
<mapper namespace="com.bean.dao.DbBirdexpresstypeMapper">
  <resultMap id="BaseResultMap" type="com.bean.model.DbBirdexpresstype">
    <id column="SID" jdbcType="VARCHAR" property="sid" />
    <result column="NAME" jdbcType="VARCHAR" property="name" />
    <result column="SPECIALTYPE" jdbcType="VARCHAR" property="specialtype" />
    <result column="OPERTIME" jdbcType="TIMESTAMP" property="opertime" />
  </resultMap>
  <sql id="Base_Column_List">
    SID, 'NAME', SPECIALTYPE, OPERTIME
  </sql>
  <select id="selectByPrimaryKey" parameterType="java.lang.String" resultMap="BaseResultMap">
    select 
    <include refid="Base_Column_List" />
    from db_birdexpresstype
    where SID = #{sid,jdbcType=VARCHAR}
  </select>
  <delete id="deleteByPrimaryKey" parameterType="java.lang.String">
    delete from db_birdexpresstype
    where SID = #{sid,jdbcType=VARCHAR}
  </delete>
  <insert id="insert" parameterType="com.bean.model.DbBirdexpresstype">
    insert into db_birdexpresstype (SID, 'NAME', SPECIALTYPE, 
      OPERTIME)
    values (#{sid,jdbcType=VARCHAR}, #{name,jdbcType=VARCHAR}, #{specialtype,jdbcType=VARCHAR}, 
      #{opertime,jdbcType=TIMESTAMP})
  </insert>
  <insert id="insertSelective" parameterType="com.bean.model.DbBirdexpresstype">
    insert into db_birdexpresstype
    <trim prefix="(" suffix=")" suffixOverrides=",">
      <if test="sid != null">
        SID,
      </if>
      <if test="name != null">
        'NAME',
      </if>
      <if test="specialtype != null">
        SPECIALTYPE,
      </if>
      <if test="opertime != null">
        OPERTIME,
      </if>
    </trim>
    <trim prefix="values (" suffix=")" suffixOverrides=",">
      <if test="sid != null">
        #{sid,jdbcType=VARCHAR},
      </if>
      <if test="name != null">
        #{name,jdbcType=VARCHAR},
      </if>
      <if test="specialtype != null">
        #{specialtype,jdbcType=VARCHAR},
      </if>
      <if test="opertime != null">
        #{opertime,jdbcType=TIMESTAMP},
      </if>
    </trim>
  </insert>
  <update id="updateByPrimaryKeySelective" parameterType="com.bean.model.DbBirdexpresstype">
    update db_birdexpresstype
    <set>
      <if test="name != null">
        'NAME' = #{name,jdbcType=VARCHAR},
      </if>
      <if test="specialtype != null">
        SPECIALTYPE = #{specialtype,jdbcType=VARCHAR},
      </if>
      <if test="opertime != null">
        OPERTIME = #{opertime,jdbcType=TIMESTAMP},
      </if>
    </set>
    where SID = #{sid,jdbcType=VARCHAR}
  </update>
  <update id="updateByPrimaryKey" parameterType="com.bean.model.DbBirdexpresstype">
    update db_birdexpresstype
    set 'NAME' = #{name,jdbcType=VARCHAR},
      SPECIALTYPE = #{specialtype,jdbcType=VARCHAR},
      OPERTIME = #{opertime,jdbcType=TIMESTAMP}
    where SID = #{sid,jdbcType=VARCHAR}
  </update>
</mapper>